zkvvm.py
zkvvm-0.1.0.dist-info/entry_points.txt
zkvvm-0.1.0.dist-info/LICENSE
zkvvm-0.1.0.dist-info/WHEEL
zkvvm-0.1.0.dist-info/METADATA
zkvvm-0.1.0.dist-info/RECORD
