Metadata-Version: 2.1
Name: zkvvm
Version: 0.1.0
Summary: zkVyper version manager
License: MIT
Author: Edward Amor
Author-email: edward.amor3@gmail.com
Requires-Python: >=3.8,<4.0
Classifier: License :: OSI Approved :: MIT License
Classifier: Programming Language :: Python :: 3
Classifier: Programming Language :: Python :: 3.8
Classifier: Programming Language :: Python :: 3.9
Classifier: Programming Language :: Python :: 3.10
Classifier: Programming Language :: Python :: 3.11
Requires-Dist: appdirs (>=1.4.4,<2.0.0)
Requires-Dist: tqdm (>=4.64.1,<5.0.0)
Requires-Dist: vvm (>=0.1.0,<0.2.0)
